csv_analyzer_extended/__init__.py
csv_analyzer_extended/analyzer.py
csv_analyzer_extended/exporter.py
csv_analyzer_extended/filter.py
csv_analyzer_extended/helper.py
csv_analyzer_extended/sorter.py
csv_analyzer_extended/summarizer.py
csv_analyzer_extended-1.2.dist-info/METADATA
csv_analyzer_extended-1.2.dist-info/WHEEL
csv_analyzer_extended-1.2.dist-info/top_level.txt
csv_analyzer_extended-1.2.dist-info/RECORD
