Metadata-Version: 2.1
Name: csv_analyzer_extended
Version: 1.2
Summary: A CSV analyzer tool with extended filtering and analysis capabilities
Author: Ralf Krümmel
Author-email: ralf.kruemmel+python@outlook.de
License: MIT
